tests/__init__.py
tests/annotators/__init__.py
tests/annotators/positionannotators/__init__.py
tests/annotators/positionannotators/sp1basedtranscriptfeatureannotator/__init__.py
tests/annotators/positionannotators/sp1basedtranscriptfeatureannotator/test_erbb2.py
tests/annotators/positionannotators/sp1basedtranscriptfeatureannotator/test_tert.py
tests/annotators/rangeannotators/__init__.py
tests/annotators/rangeannotators/genomicrange1basedtranscriptfeatureannotator/__init__.py
tests/annotators/rangeannotators/genomicrange1basedtranscriptfeatureannotator/test_erbb2.py
tests/annotators/rangeannotators/genomicrange1basedtranscriptfeatureannotator/test_tert.py
tests/models/__init__.py
tests/models/genomicpositions/__init__.py
tests/models/genomicpositions/test_genomicrange.py
tests/models/genomicpositions/test_genomicrange0based.py
tests/models/genomicpositions/test_genomicrange1based.py
tests/models/genomicpositions/test_sp.py
tests/models/genomicpositions/test_sp0based.py
tests/models/genomicpositions/test_sp1based.py
tests/transcriptfeaturescreators/__init__.py
tests/transcriptfeaturescreators/transcriptfeaturescreator/__init__.py
tests/transcriptfeaturescreators/transcriptfeaturescreator/test_erbb2_nm_004448_2.py
tests/transcriptfeaturescreators/txexonfetcher/__init__.py
tests/transcriptfeaturescreators/txexonfetcher/test_erbb2_nm_004448_2.py
transcriptfeatures/__init__.py
transcriptfeatures/annotators/__init__.py
transcriptfeatures/annotators/positionannotators/__init__.py
transcriptfeatures/annotators/positionannotators/sp1basedtranscriptfeatureannotator.py
transcriptfeatures/annotators/rangeannotators/__init__.py
transcriptfeatures/annotators/rangeannotators/genomicrange1basedtranscriptfeatureannotator.py
transcriptfeatures/annotators/rangeannotators/transcriptfeaturerangeannotation.py
transcriptfeatures/models/__init__.py
transcriptfeatures/models/body.py
transcriptfeatures/models/exon.py
transcriptfeatures/models/intron.py
transcriptfeatures/models/promoter.py
transcriptfeatures-0.0.1.dist-info/METADATA
transcriptfeatures-0.0.1.dist-info/WHEEL
transcriptfeatures-0.0.1.dist-info/top_level.txt
transcriptfeatures-0.0.1.dist-info/RECORD
